custom_app_store/__init__.py
custom_app_store/custom_app_store.py
custom_data_store-0.1.1.dist-info/LICENSE
custom_data_store-0.1.1.dist-info/METADATA
custom_data_store-0.1.1.dist-info/WHEEL
custom_data_store-0.1.1.dist-info/top_level.txt
custom_data_store-0.1.1.dist-info/RECORD
